sqlalchemy_modelid/__init__.py
sqlalchemy_modelid-0.0.3.dist-info/LICENSE
sqlalchemy_modelid-0.0.3.dist-info/METADATA
sqlalchemy_modelid-0.0.3.dist-info/WHEEL
sqlalchemy_modelid-0.0.3.dist-info/top_level.txt
sqlalchemy_modelid-0.0.3.dist-info/RECORD
